deepfilter_multimedia/__init__.py
deepfilter_multimedia/__main__.py
deepfilter_multimedia/cli.py
deepfilter_multimedia/core.py
deepfilter_multimedia-0.1.3.dist-info/licenses/LICENSE
deepfilter_multimedia-0.1.3.dist-info/METADATA
deepfilter_multimedia-0.1.3.dist-info/WHEEL
deepfilter_multimedia-0.1.3.dist-info/entry_points.txt
deepfilter_multimedia-0.1.3.dist-info/top_level.txt
deepfilter_multimedia-0.1.3.dist-info/RECORD
