Metadata-Version: 2.4
Name: deepfilter-multimedia
Version: 0.1.3
Summary: Noise reduction for audio and video files using DeepFilterNet
Home-page: https://github.com/svemyh/deepfilter-multimedia
Author: Sveinung Myhre
Author-email: 
License: MIT
Project-URL: Homepage, https://github.com/svemyh/deepfilter-multimedia
Project-URL: Bug Reports, https://github.com/svemyh/deepfilter-multimedia/issues
Project-URL: Source, https://github.com/svemyh/deepfilter-multimedia
Project-URL: DeepFilterNet, https://github.com/Rikorose/DeepFilterNet
Keywords: audio,video,noise-reduction,deepfilternet,speech-enhancement
Classifier: Development Status :: 3 - Alpha
Classifier: Intended Audience :: Developers
Classifier: Intended Audience :: End Users/Desktop
Classifier: Topic :: Multimedia :: Sound/Audio :: Analysis
Classifier: Topic :: Multimedia :: Video
Classifier: License :: OSI Approved :: MIT License
Classifier: Programming Language :: Python :: 3
Classifier: Programming Language :: Python :: 3.8
Classifier: Programming Language :: Python :: 3.9
Classifier: Programming Language :: Python :: 3.10
Classifier: Programming Language :: Python :: 3.11
Classifier: Operating System :: OS Independent
Requires-Python: >=3.8
License-File: LICENSE
Requires-Dist: deepfilternet>=0.5.0
Requires-Dist: torch>=1.9.0
Requires-Dist: torchaudio>=0.9.0
Requires-Dist: soundfile>=0.12.0
Provides-Extra: dev
Requires-Dist: pytest>=7.0; extra == "dev"
Requires-Dist: black>=22.0; extra == "dev"
Requires-Dist: flake8>=4.0; extra == "dev"
Requires-Dist: mypy>=0.950; extra == "dev"
Dynamic: home-page
Dynamic: license-file
Dynamic: requires-python
